{ 
  "favorites": [],
  "sets":
  {
    "kolay": [
      {
        "id": "kolay-set-1",
        "title": "Kolay Set 1",
        "totalWords": 10,
      "completedCount": 0,
      "learnedCount": 0,
      "lastReviewed": null,
      "completedTests": {
        "LearnTest": 0,
        "MatchTest": 0,
        "TranslateTest": 0,
        "FillTest": 0
      },
      "stars": 0,
      "createdAt": "2025-09-04T00:00:00Z",
      "words": [
        {
          "id": "w001",
          "word": "abundant",
          "meaning": "bol, çok",
          "example": "The region has abundant rainfalls in spring.",
          "tags": ["adj", "common"]
        },
        {
          "id": "w002",
          "word": "basic",
          "meaning": "temel",
          "example": "Start with the basic concepts first.",
          "tags": ["adj", "common"]
        },
        {
          "id": "w003",
          "word": "confirm",
          "meaning": "onaylamak",
          "example": "Please confirm your appointment time.",
          "tags": ["verb", "common"]
        },
        {
          "id": "w004",
          "word": "deliver",
          "meaning": "teslim etmek",
          "example": "They will deliver the package tomorrow.",
          "tags": ["verb"]
        },
        {
          "id": "w005",
          "word": "eager",
          "meaning": "hevesli",
          "example": "She was eager to start her new job.",
          "tags": ["adj"]
        },
        {
          "id": "w006",
          "word": "focus",
          "meaning": "odaklanmak",
          "example": "Focus on the task at hand.",
          "tags": ["verb", "common"]
        },
        {
          "id": "w007",
          "word": "genuine",
          "meaning": "samimi, gerçek",
          "example": "Her apology seemed genuine.",
          "tags": ["adj"]
        },
        {
          "id": "w008",
          "word": "habit",
          "meaning": "alışkanlık",
          "example": "Reading is a healthy habit.",
          "tags": ["noun"]
        },
        {
          "id": "w009",
          "word": "isolate",
          "meaning": "izole etmek",
          "example": "They had to isolate the infected area.",
          "tags": ["verb"]
        },
        {
          "id": "w010",
          "word": "journey",
          "meaning": "yolculuk",
          "example": "The journey took several days.",
          "tags": ["noun"]
        }
      ]
    },
    {
      "id": "kolay-set-2",
      "title": "Kolay Set 2",
      "totalWords": 10,
      "completedCount": 0,
      "learnedCount": 0,
      "lastReviewed": null,
      "completedTests": {
        "LearnTest": 0,
        "MatchTest": 0,
        "TranslateTest": 0,
        "FillTest": 0
      },
      "stars": 0,
      "createdAt": "2025-09-04T00:00:00Z",
      "words": [
        {
          "id": "w031",
          "word": "keenly",
          "meaning": "kesinlikle, güçlü şekilde",
          "example": "She felt the cold keenly.",
          "tags": ["adv"]
        },
        {
          "id": "w032",
          "word": "limit",
          "meaning": "sınır",
          "example": "You should know your limit.",
          "tags": ["noun", "common"]
        },
        {
          "id": "w033",
          "word": "mend",
          "meaning": "tamir etmek",
          "example": "He will mend the broken chair.",
          "tags": ["verb"]
        },
        {
          "id": "w034",
          "word": "narrow",
          "meaning": "dar",
          "example": "The path becomes narrow ahead.",
          "tags": ["adj"]
        },
        {
          "id": "w035",
          "word": "oppose",
          "meaning": "karşı çıkmak",
          "example": "Many oppose the plan.",
          "tags": ["verb"]
        },
        {
          "id": "w036",
          "word": "pioneer",
          "meaning": "öncü",
          "example": "She was a pioneer in the field.",
          "tags": ["noun"]
        },
        {
          "id": "w037",
          "word": "quell",
          "meaning": "bastırmak",
          "example": "The police tried to quell the unrest.",
          "tags": ["verb"]
        },
        {
          "id": "w038",
          "word": "rational",
          "meaning": "akla uygun",
          "example": "Make a rational decision.",
          "tags": ["adj"]
        },
        {
          "id": "w047",
          "word": "aloof",
          "meaning": "uzak, soğuk",
          "example": "She remained aloof from the discussion.",
          "tags": ["adj"]
        },
        {
          "id": "w048",
          "word": "blunt",
          "meaning": "açık sözlü; körelmiş",
          "example": "He was blunt about his opinion.",
          "tags": ["adj"]
        }
      ]
    },
    {
      "id": "kolay-set-3",
      "title": "Kolay Set 3",
      "totalWords": 10,
      "completedCount": 0,
      "learnedCount": 0,
      "lastReviewed": null,
      "completedTests": {
        "LearnTest": 0,
        "MatchTest": 0,
        "TranslateTest": 0,
        "FillTest": 0
      },
      "stars": 0,
      "createdAt": "2025-09-04T00:00:00Z",
      "words": [
        {
          "id": "w049",
          "word": "candid",
          "meaning": "samimi",
          "example": "She gave a candid interview.",
          "tags": ["adj"]
        },
        {
          "id": "w050",
          "word": "deter",
          "meaning": "vazgeçirmek",
          "example": "High costs may deter investors.",
          "tags": ["verb"]
        },
        {
          "id": "w057",
          "word": "knack",
          "meaning": "beceri",
          "example": "She has a knack for languages.",
          "tags": ["noun"]
        },
        {
          "id": "w063",
          "word": "quell",
          "meaning": "bastırmak",
          "example": "The police tried to quell the unrest.",
          "tags": ["verb"]
        },
        {
          "id": "w069",
          "word": "wane",
          "meaning": "azalmak",
          "example": "Interest in the show began to wane.",
          "tags": ["verb"]
        },
        {
          "id": "w078",
          "word": "glimmer",
          "meaning": "hafif ışık",
          "example": "A glimmer of hope remained.",
          "tags": ["noun"]
        },
        {
          "id": "w079",
          "word": "heed",
          "meaning": "dikkate almak",
          "example": "You should heed the warning.",
          "tags": ["verb"]
        },
        {
          "id": "w081",
          "word": "jovial",
          "meaning": "neşeli",
          "example": "He was in a jovial mood.",
          "tags": ["adj"]
        },
        {
          "id": "w085",
          "word": "novice",
          "meaning": "acemi",
          "example": "I am still a novice at coding.",
          "tags": ["noun"]
        },
        {
          "id": "w093",
          "word": "vex",
          "meaning": "can sıkmak",
          "example": "Small mistakes can vex the manager.",
          "tags": ["verb"]
        }
      ]
    },
    {
      "id": "kolay-set-4",
      "title": "Kolay Set 4",
      "totalWords": 2,
      "completedCount": 0,
      "learnedCount": 0,
      "lastReviewed": null,
      "completedTests": {
        "LearnTest": 0,
        "MatchTest": 0,
        "TranslateTest": 0,
        "FillTest": 0
      },
      "stars": 0,
      "createdAt": "2025-09-04T00:00:00Z",
      "words": [
        {
          "id": "w098",
          "word": "banal",
          "meaning": "sıradan, banal",
          "example": "The plot was fairly banal.",
          "tags": ["adj"]
        },
        {
          "id": "w100",
          "word": "diligent",
          "meaning": "gayretli",
          "example": "He is a diligent student.",
          "tags": ["adj"]
        }
      ]
    }
  ],
  "orta": [
    {
      "id": "orta-set-1",
      "title": "Orta Set 1",
      "totalWords": 10,
      "completedCount": 0,
      "learnedCount": 0,
      "lastReviewed": null,
      "completedTests": {
        "LearnTest": 0,
        "MatchTest": 0,
        "TranslateTest": 0,
        "FillTest": 0
      },
      "stars": 0,
      "createdAt": "2025-09-04T00:00:00Z",
      "words": [
        {
          "id": "w011",
          "word": "keen",
          "meaning": "hevesli, istekli",
          "example": "He is keen to improve his skills.",
          "tags": ["adj"]
        },
        {
          "id": "w012",
          "word": "lapse",
          "meaning": "geçici hata",
          "example": "A lapse in concentration caused the mistake.",
          "tags": ["noun"]
        },
        {
          "id": "w013",
          "word": "magnitude",
          "meaning": "büyüklük",
          "example": "They underestimated the magnitude of the problem.",
          "tags": ["noun"]
        },
        {
          "id": "w014",
          "word": "navigate",
          "meaning": "yönlendirmek",
          "example": "She had to navigate the complex system.",
          "tags": ["verb"]
        },
        {
          "id": "w015",
          "word": "oblige",
          "meaning": "zorunlu kılmak",
          "example": "Circumstances oblige us to act now.",
          "tags": ["verb"]
        },
        {
          "id": "w016",
          "word": "pertain",
          "meaning": "ait olmak",
          "example": "The rules pertain to all members.",
          "tags": ["verb"]
        },
        {
          "id": "w017",
          "word": "quaint",
          "meaning": "tuhaf ama hoş",
          "example": "They live in a quaint village.",
          "tags": ["adj"]
        },
        {
          "id": "w018",
          "word": "refine",
          "meaning": "iyileştirmek",
          "example": "We need to refine our strategy.",
          "tags": ["verb"]
        },
        {
          "id": "w019",
          "word": "subtle",
          "meaning": "ince, zor algılanan",
          "example": "There is a subtle difference between the two.",
          "tags": ["adj"]
        },
        {
          "id": "w020",
          "word": "tactic",
          "meaning": "taktik",
          "example": "They discussed the best tactic for the game.",
          "tags": ["noun"]
        }
      ]
    },
    {
      "id": "orta-set-2",
      "title": "Orta Set 2",
      "totalWords": 10,
      "completedCount": 0,
      "learnedCount": 0,
      "lastReviewed": null,
      "completedTests": {
        "LearnTest": 0,
        "MatchTest": 0,
        "TranslateTest": 0,
        "FillTest": 0
      },
      "stars": 0,
      "createdAt": "2025-09-04T00:00:00Z",
      "words": [
        {
          "id": "w039",
          "word": "salient",
          "meaning": "belirgin",
          "example": "She pointed out the salient features.",
          "tags": ["adj"]
        },
        {
          "id": "w040",
          "word": "transcend",
          "meaning": "aşmak",
          "example": "His achievements transcend expectation.",
          "tags": ["verb", "advanced"]
        },
        {
          "id": "w043",
          "word": "wary",
          "meaning": "temkinli",
          "example": "Be wary of strangers.",
          "tags": ["adj", "common"]
        },
        {
          "id": "w045",
          "word": "yonder",
          "meaning": "uzakta",
          "example": "Look at the house yonder.",
          "tags": ["adv", "archaic"]
        },
        {
          "id": "w046",
          "word": "zealous",
          "meaning": "coşkulu, gayretli",
          "example": "He is zealous about his work.",
          "tags": ["adj"]
        },
        {
          "id": "w051",
          "word": "elicit",
          "meaning": "ortaya çıkarmak",
          "example": "The question elicited a strong response.",
          "tags": ["verb"]
        },
        {
          "id": "w052",
          "word": "futile",
          "meaning": "nafile",
          "example": "It was futile to argue further.",
          "tags": ["adj"]
        },
        {
          "id": "w053",
          "word": "gratify",
          "meaning": "memnun etmek",
          "example": "He was gratified by the praise.",
          "tags": ["verb"]
        },
        {
          "id": "w054",
          "word": "hasten",
          "meaning": "hızlandırmak",
          "example": "They hastened to finish the work.",
          "tags": ["verb"]
        },
        {
          "id": "w055",
          "word": "impede",
          "meaning": "engellemek",
          "example": "Roadworks will impede traffic.",
          "tags": ["verb"]
        }
      ]
    },
    {
      "id": "orta-set-3",
      "title": "Orta Set 3",
      "totalWords": 10,
      "completedCount": 0,
      "learnedCount": 0,
      "lastReviewed": null,
      "completedTests": {
        "LearnTest": 0,
        "MatchTest": 0,
        "TranslateTest": 0,
        "FillTest": 0
      },
      "stars": 0,
      "createdAt": "2025-09-04T00:00:00Z",
      "words": [
        {
          "id": "w058",
          "word": "lucid",
          "meaning": "açık, anlaşılır",
          "example": "Her explanation was lucid and helpful.",
          "tags": ["adj"]
        },
        {
          "id": "w061",
          "word": "oblige",
          "meaning": "zorunlu kılmak",
          "example": "Circumstances oblige us to act now.",
          "tags": ["verb"]
        },
        {
          "id": "w065",
          "word": "stoic",
          "meaning": "sakin, metin",
          "example": "He remained stoic in the face of danger.",
          "tags": ["adj"]
        },
        {
          "id": "w067",
          "word": "utilize",
          "meaning": "kullanmak",
          "example": "We should utilize available resources.",
          "tags": ["verb"]
        },
        {
          "id": "w068",
          "word": "vigilant",
          "meaning": "tetikte",
          "example": "Stay vigilant during the trip.",
          "tags": ["adj"]
        },
        {
          "id": "w070",
          "word": "yearn",
          "meaning": "özlem duymak",
          "example": "She began to yearn for home.",
          "tags": ["verb"]
        },
        {
          "id": "w072",
          "word": "acclaim",
          "meaning": "övgü",
          "example": "The film received critical acclaim.",
          "tags": ["noun"]
        },
        {
          "id": "w073",
          "word": "baffle",
          "meaning": "şaşırtmak",
          "example": "The mystery continues to baffle experts.",
          "tags": ["verb"]
        },
        {
          "id": "w074",
          "word": "coherent",
          "meaning": "tutarlı",
          "example": "Her argument was coherent and strong.",
          "tags": ["adj"]
        },
        {
          "id": "w077",
          "word": "fortify",
          "meaning": "güçlendirmek",
          "example": "They fortify the walls against attack.",
          "tags": ["verb"]
        }
      ]
    },
    {
      "id": "orta-set-4",
      "title": "Orta Set 4",
      "totalWords": 8,
      "completedCount": 0,
      "learnedCount": 0,
      "lastReviewed": null,
      "completedTests": {
        "LearnTest": 0,
        "MatchTest": 0,
        "TranslateTest": 0,
        "FillTest": 0
      },
      "stars": 0,
      "createdAt": "2025-09-04T00:00:00Z",
      "words": [
        {
          "id": "w080",
          "word": "insight",
          "meaning": "içgörü",
          "example": "Her insight helped solve the problem.",
          "tags": ["noun"]
        },
        {
          "id": "w082",
          "word": "knoll",
          "meaning": "tepecik",
          "example": "They sat on the grassy knoll.",
          "tags": ["noun", "archaic"]
        },
        {
          "id": "w086",
          "word": "obscure",
          "meaning": "gizli, belirsiz",
          "example": "The reference was obscure.",
          "tags": ["adj"]
        },
        {
          "id": "w089",
          "word": "rampant",
          "meaning": "kontrolsüz",
          "example": "Corruption was rampant in the system.",
          "tags": ["adj"]
        },
        {
          "id": "w091",
          "word": "tenet",
          "meaning": "ilke",
          "example": "One tenet of the theory is simplicity.",
          "tags": ["noun"]
        },
        {
          "id": "w095",
          "word": "yoke",
          "meaning": "boyunduruk; bağlamak",
          "example": "The farmers used a yoke for the oxen.",
          "tags": ["noun", "verb"]
        },
        {
          "id": "w097",
          "word": "ardent",
          "meaning": "ateşli, hevesli",
          "example": "She is an ardent supporter.",
          "tags": ["adj"]
        },
        {
          "id": "w099",
          "word": "clamor",
          "meaning": "yüksek sesle talep etmek",
          "example": "Crowds clamored for change.",
          "tags": ["verb", "noun"]
        }
      ]
    }
  ],
  "zor": [
    {
      "id": "zor-set-1",
      "title": "Zor Set 1",
      "totalWords": 10,
      "completedCount": 0,
      "learnedCount": 0,
      "lastReviewed": null,
      "completedTests": {
        "LearnTest": 0,
        "MatchTest": 0,
        "TranslateTest": 0,
        "FillTest": 0
      },
      "stars": 0,
      "createdAt": "2025-09-04T00:00:00Z",
      "words": [
        {
          "id": "w021",
          "word": "aberration",
          "meaning": "sapma, anormallik",
          "example": "The result was an aberration from the norm.",
          "tags": ["noun", "advanced"]
        },
        {
          "id": "w022",
          "word": "belligerent",
          "meaning": "savaşçı, agresif",
          "example": "His belligerent attitude caused problems.",
          "tags": ["adj", "advanced"]
        },
        {
          "id": "w023",
          "word": "circumvent",
          "meaning": "atlatmak, dolanmak",
          "example": "They tried to circumvent the rules.",
          "tags": ["verb", "advanced"]
        },
        {
          "id": "w024",
          "word": "deleterious",
          "meaning": "zararlı",
          "example": "Smoking has deleterious effects.",
          "tags": ["adj", "advanced"]
        },
        {
          "id": "w025",
          "word": "euphony",
          "meaning": "hoş ses",
          "example": "The poem had a pleasing euphony.",
          "tags": ["noun", "advanced"]
        },
        {
          "id": "w026",
          "word": "forlorn",
          "meaning": "umutsuz, kimsesiz",
          "example": "The puppy looked forlorn and lonely.",
          "tags": ["adj"]
        },
        {
          "id": "w027",
          "word": "gregarious",
          "meaning": "sosyal, topluluk seven",
          "example": "He is very gregarious and outgoing.",
          "tags": ["adj", "advanced"]
        },
        {
          "id": "w028",
          "word": "harangue",
          "meaning": "nutuk atmak",
          "example": "The coach delivered a long harangue.",
          "tags": ["verb", "advanced"]
        },
        {
          "id": "w029",
          "word": "imbue",
          "meaning": "aşılamak",
          "example": "The teacher aims to imbue students with curiosity.",
          "tags": ["verb"]
        },
        {
          "id": "w030",
          "word": "juxtapose",
          "meaning": "yan yana koymak",
          "example": "The artist juxtaposed light and dark elements.",
          "tags": ["verb", "advanced"]
        }
      ]
    },
    {
      "id": "zor-set-2",
      "title": "Zor Set 2",
      "totalWords": 10,
      "completedCount": 0,
      "learnedCount": 0,
      "lastReviewed": null,
      "completedTests": {
        "LearnTest": 0,
        "MatchTest": 0,
        "TranslateTest": 0,
        "FillTest": 0
      },
      "stars": 0,
      "createdAt": "2025-09-04T00:00:00Z",
      "words": [
        {
          "id": "w041",
          "word": "ubiquitous",
          "meaning": "her yerde bulunan",
          "example": "Smartphones are ubiquitous today.",
          "tags": ["adj", "advanced"]
        },
        {
          "id": "w042",
          "word": "venerate",
          "meaning": "saygı göstermek",
          "example": "They venerate their elders.",
          "tags": ["verb", "advanced"]
        },
        {
          "id": "w044",
          "word": "xenial",
          "meaning": "misafirperver",
          "example": "The hosts were xenial to their guests.",
          "tags": ["adj", "advanced"]
        },
        {
          "id": "w056",
          "word": "jaded",
          "meaning": "bıkmış",
          "example": "He felt jaded after years of work.",
          "tags": ["adj"]
        },
        {
          "id": "w059",
          "word": "mettle",
          "meaning": "cesaret, dayanıklılık",
          "example": "He proved his mettle during the challenge.",
          "tags": ["noun", "advanced"]
        },
        {
          "id": "w060",
          "word": "nuance",
          "meaning": "ince fark",
          "example": "He understood every nuance of the argument.",
          "tags": ["noun", "advanced"]
        },
        {
          "id": "w062",
          "word": "palpable",
          "meaning": "dokunulur, açık",
          "example": "There was a palpable tension in the room.",
          "tags": ["adj", "advanced"]
        },
        {
          "id": "w064",
          "word": "rescind",
          "meaning": "feshetmek",
          "example": "They decided to rescind the policy.",
          "tags": ["verb", "advanced"]
        },
        {
          "id": "w066",
          "word": "tenuous",
          "meaning": "zayıf, hassas",
          "example": "The agreement was tenuous at best.",
          "tags": ["adj", "advanced"]
        },
        {
          "id": "w071",
          "word": "zephyr",
          "meaning": "hafif rüzgar",
          "example": "A gentle zephyr cooled the room.",
          "tags": ["noun", "advanced"]
        }
      ]
    },
    {
      "id": "zor-set-3",
      "title": "Zor Set 3",
      "totalWords": 10,
      "completedCount": 0,
      "learnedCount": 0,
      "lastReviewed": null,
      "completedTests": {
        "LearnTest": 0,
        "MatchTest": 0,
        "TranslateTest": 0,
        "FillTest": 0
      },
      "stars": 0,
      "createdAt": "2025-09-04T00:00:00Z",
      "words": [
        {
          "id": "w075",
          "word": "dexterous",
          "meaning": "becerikli",
          "example": "He is dexterous with his hands.",
          "tags": ["adj", "advanced"]
        },
        {
          "id": "w076",
          "word": "elusive",
          "meaning": "zor yakalanan",
          "example": "The solution remained elusive.",
          "tags": ["adj"]
        },
        {
          "id": "w083",
          "word": "lucent",
          "meaning": "parlak, ışıklı",
          "example": "The lucent surface reflected the sun.",
          "tags": ["adj", "advanced"]
        },
        {
          "id": "w084",
          "word": "maverick",
          "meaning": "bağımsız kişi",
          "example": "He is a maverick in the industry.",
          "tags": ["noun", "advanced"]
        },
        {
          "id": "w087",
          "word": "paradox",
          "meaning": "çelişki",
          "example": "Life is full of paradoxes.",
          "tags": ["noun", "advanced"]
        },
        {
          "id": "w088",
          "word": "quixotic",
          "meaning": "hayalci, gerçekçi olmayan",
          "example": "His plans were quixotic but charming.",
          "tags": ["adj", "advanced"]
        },
        {
          "id": "w090",
          "word": "sagacious",
          "meaning": "akıllı, bilge",
          "example": "She offered sagacious advice.",
          "tags": ["adj", "advanced"]
        },
        {
          "id": "w092",
          "word": "untoward",
          "meaning": "uygunsuz; nahoş",
          "example": "Untoward events delayed the project.",
          "tags": ["adj"]
        },
        {
          "id": "w094",
          "word": "wheedle",
          "meaning": "tatlı sözle ikna etmek",
          "example": "He tried to wheedle extra time from the teacher.",
          "tags": ["verb", "advanced"]
        },
        {
          "id": "w096",
          "word": "zenith",
          "meaning": "zirve",
          "example": "They reached the zenith of their career.",
          "tags": ["noun", "advanced"]
        }
      ]
    }
  ]}
}